[
  {
    "name": "Amazonia",
    "slug": "amazonia",
    "ingredients": ["Maracuja", "Mandarine", "Gingembre", "Menthe"]
  },
  {
    "name": "Blackberry",
    "slug": "blackberry",
    "ingredients": ["Mûre Andine", "Ananas", "Jus de citron"]
  },
  {
    "name": "Corossol Colada",
    "slug": "corossol-colada",
    "ingredients": ["Corossol", "Ananas", "Lait de coco", "Menthe"]
  },
  {
    "name": "Lulada",
    "slug": "lulada",
    "ingredients": ["Lulo", "Mangue", "Jus de citron"]
  },
  {
    "name": "Pili Tropical",
    "slug": "pili-tropical",
    "ingredients": ["Papaye ou goyave", "Maracuja", "Piment d'espelette", "Menthe"]
  }
]
